deeppages/__init__.py
deeppages/admin.py
deeppages/apps.py
deeppages/exceptions.py
deeppages/loaders.py
deeppages/middleware.py
deeppages/models.py
deeppages/signals.py
deeppages/tests.py
deeppages/urls.py
deeppages/utils.py
deeppages/views.py
deeppages/migrations/0001_initial.py
deeppages/migrations/0002_auto_20180719_1509.py
deeppages/migrations/0003_page_slug.py
deeppages/migrations/0004_auto_20191018_0914.py
deeppages/migrations/__init__.py
deeppages-0.2.4.dist-info/LICENSE
deeppages-0.2.4.dist-info/METADATA
deeppages-0.2.4.dist-info/WHEEL
deeppages-0.2.4.dist-info/top_level.txt
deeppages-0.2.4.dist-info/RECORD
