Metadata-Version: 2.1
Name: deeppages
Version: 0.2.4
Summary: Django's database stored web content processor
Home-page: https://github.com/ricardofalasca/deep-pages
Author: Ricardo Falasca
Author-email: ricardo@falasca.com.br
License: MIT
Platform: UNKNOWN
Classifier: Development Status :: 4 - Beta
Classifier: Environment :: Web Environment
Classifier: Framework :: Django
Classifier: Framework :: Django :: 1.10
Classifier: Framework :: Django :: 1.11
Classifier: Framework :: Django :: 2.0
Classifier: Framework :: Django :: 2.1
Classifier: Operating System :: OS Independent
Classifier: Programming Language :: Python
Classifier: Programming Language :: Python :: 3
Classifier: Programming Language :: Python :: 3.4
Classifier: Programming Language :: Python :: 3.5
Classifier: Programming Language :: Python :: 3.6
Classifier: Topic :: Internet :: WWW/HTTP
Requires-Dist: django (>1.10)
Requires-Dist: django-autoslug (>=1.9.4)
